behave_models_steps/__init__.py
behave_models_steps/utils.py
behave_models_steps/steps/__init__.py
behave_models_steps-0.1.1.dist-info/DESCRIPTION.rst
behave_models_steps-0.1.1.dist-info/METADATA
behave_models_steps-0.1.1.dist-info/RECORD
behave_models_steps-0.1.1.dist-info/WHEEL
behave_models_steps-0.1.1.dist-info/metadata.json
behave_models_steps-0.1.1.dist-info/top_level.txt
